flater/__init__.py
flater/basic.py
flater/library/__init__.py
flater/test.1.py
flater/test.realtaiizor.1.py
flater/winforms/__init__.py
flater/winforms/application.py
flater/winforms/button.py
flater/winforms/control.py
flater/winforms/form.py
flater/winforms/label.py
flater/winforms/py.ico
flater/winforms/realtaiizor/__init__.py
flater/winforms/tooltip.py
flater/wpf/__init__.py
flater/wpf/code.py
flater/wpf/gui.xaml
flater/wpf/thread.py
flater/wpf/window.py
flaterlog.py
flater-0.1.2.dist-info/METADATA
flater-0.1.2.dist-info/WHEEL
flater-0.1.2.dist-info/RECORD
