Metadata-Version: 2.1
Name: flater
Version: 0.1.2
Summary: WinForms UI Pack
Author: XiangQinxi
Author-email: XiangQinxi@outlook.com
Requires-Python: >=3.7,<4.0
Classifier: Programming Language :: Python :: 3
Classifier: Programming Language :: Python :: 3.7
Classifier: Programming Language :: Python :: 3.8
Classifier: Programming Language :: Python :: 3.9
Classifier: Programming Language :: Python :: 3.10
Classifier: Programming Language :: Python :: 3.11
Requires-Dist: colorama (>=0.4.6,<0.5.0)
Requires-Dist: darkdetect (>=0.8.0,<0.9.0)
Requires-Dist: pythonnet (>=3.0.3,<4.0.0)
